dao_treasury__mypyc.cpython-312-x86_64-linux-musl.so
dao_treasury/ENVIRONMENT_VARIABLES.py
dao_treasury/__init__.py
dao_treasury/_docker.cpython-312-x86_64-linux-musl.so
dao_treasury/_docker.py
dao_treasury/_nicknames.cpython-312-x86_64-linux-musl.so
dao_treasury/_nicknames.py
dao_treasury/_wallet.cpython-312-x86_64-linux-musl.so
dao_treasury/_wallet.py
dao_treasury/constants.cpython-312-x86_64-linux-musl.so
dao_treasury/constants.py
dao_treasury/db.py
dao_treasury/docker-compose.yaml
dao_treasury/main.py
dao_treasury/py.typed
dao_treasury/treasury.py
dao_treasury/types.cpython-312-x86_64-linux-musl.so
dao_treasury/types.py
dao_treasury/.grafana/provisioning/dashboards/dashboards.yaml
dao_treasury/.grafana/provisioning/dashboards/breakdowns/Expenses.json
dao_treasury/.grafana/provisioning/dashboards/breakdowns/Revenue.json
dao_treasury/.grafana/provisioning/dashboards/streams/LlamaPay.json
dao_treasury/.grafana/provisioning/dashboards/summary/Monthly.json
dao_treasury/.grafana/provisioning/dashboards/transactions/Treasury Transactions.json
dao_treasury/.grafana/provisioning/dashboards/transactions/Unsorted Transactions.json
dao_treasury/.grafana/provisioning/dashboards/treasury/Cashflow (Including Unsorted).json
dao_treasury/.grafana/provisioning/dashboards/treasury/Cashflow.json
dao_treasury/.grafana/provisioning/dashboards/treasury/Current Treasury Assets.json
dao_treasury/.grafana/provisioning/dashboards/treasury/Historical Treasury Balances.json
dao_treasury/.grafana/provisioning/dashboards/treasury/Operating Cashflow.json
dao_treasury/.grafana/provisioning/datasources/datasources.yaml
dao_treasury/sorting/__init__.cpython-312-x86_64-linux-musl.so
dao_treasury/sorting/__init__.py
dao_treasury/sorting/_matchers.cpython-312-x86_64-linux-musl.so
dao_treasury/sorting/_matchers.py
dao_treasury/sorting/_rules.cpython-312-x86_64-linux-musl.so
dao_treasury/sorting/_rules.py
dao_treasury-1.0.0.dist-info/METADATA
dao_treasury-1.0.0.dist-info/WHEEL
dao_treasury-1.0.0.dist-info/top_level.txt
dao_treasury-1.0.0.dist-info/RECORD
